[{"SavedGroupId":24,"GroupName":"AllScenario","GroupType":"Scenario","Settings":"[{\"Name\": \"BASE\", \"Checked\": true, \"RowOrder\": 1, \"ShortName\": \"B\", \"FileStatus\": \"Consistent\", \"RecordCount\": 27068}, {\"Name\": \"B-NewTechs_SUP\", \"Checked\": false, \"RowOrder\": 2, \"ShortName\": \"SR\", \"FileStatus\": \"Consistent\", \"RecordCount\": 0}, {\"Name\": \"B-NewTechs_TRA\", \"Checked\": true, \"RowOrder\": 3, \"ShortName\": \"SR\", \"FileStatus\": \"Consistent\", \"RecordCount\": 30270}, {\"Name\": \"SysSettings\", \"Checked\": true, \"RowOrder\": 4, \"ShortName\": \"SS\", \"FileStatus\": \"Consistent\", \"RecordCount\": 2765}, {\"Name\": \"DEMAND_Base_BAU\", \"Checked\": true, \"RowOrder\": 5, \"ShortName\": \"RS\", \"FileStatus\": \"Consistent\", \"RecordCount\": 10}]","CreatedOn":"2022-11-21 11:24","DisplayCreatedOn":"2022-11-21 11:24","UserName":"jonfor"},{"SavedGroupId":25,"GroupName":"AllRegion","GroupType":"Region","Settings":"[\"Z01\", \"Z02\", \"Z03\", \"Z04\", \"Z05\", \"Z06\", \"Z07\", \"Z08\", \"Z09\", \"Z10\", \"Z11\", \"Z12\", \"Z13\", \"Z14\", \"Z15\"]","CreatedOn":"2022-11-21 11:24","DisplayCreatedOn":"2022-11-21 11:24","UserName":"jonfor"},{"SavedGroupId":26,"GroupName":"DefaultProperties","GroupType":"Properties","Settings":"{\"OptCa\": null, \"OptCr\": null, \"Damage\": 2, \"LimCol\": 0, \"LimRow\": 0, \"Oblong\": true, \"ResLim\": 50000, \"Retire\": false, \"IterLim\": 999999, \"SolPrint\": false, \"Uncertainty\": 0, \"RunInStepsOf\": 0, \"ClimateModule\": false, \"LinearVarCost\": true, \"LevelizedCosts\": 3, \"GamsOptionBratio\": \"\", \"DiscreteInvestment\": false, \"DoExtendedQaChecks\": false, \"GeneralEquilibrium\": 3, \"MidYearDiscounting\": true, \"ObjFunctionVariant\": 0, \"ShiftDiscountingBy\": 0, \"Co2CalibrationAtBoh\": false, \"UseSlackVariablesInUc\": false, \"DiscreteUnitCommitment\": false, \"EndoGenousTechLearning\": false, \"WriteBPriceforElastDem\": false, \"SaveSolutionInformation\": false, \"TsForFlowReportingTypes\": 0, \"UseLastRunAsStartingPoint\": false, \"ActivateSensitivityAnalysis\": false}","CreatedOn":"2022-11-21 11:24","DisplayCreatedOn":"2022-11-21 11:24","UserName":"jonfor"},{"SavedGroupId":27,"GroupName":"City_VB_test","GroupType":"Scenario","Settings":"[{\"Name\": \"BASE\", \"Checked\": true, \"RowOrder\": 0, \"ShortName\": \"B\"}, {\"Name\": \"B-NewTechs_SUP\", \"Checked\": true, \"RowOrder\": 1, \"ShortName\": \"SR\"}, {\"Name\": \"B-NewTechs_TRA\", \"Checked\": true, \"RowOrder\": 2, \"ShortName\": \"SR\"}, {\"Name\": \"SysSettings\", \"Checked\": true, \"RowOrder\": 3, \"ShortName\": \"SS\"}, {\"Name\": \"TRADE_PARAM\", \"Checked\": true, \"RowOrder\": 4, \"ShortName\": \"TS\"}, {\"Name\": \"DEMAND_Base_BAU\", \"Checked\": true, \"RowOrder\": 5, \"ShortName\": \"RS\"}, {\"Name\": \"DEMAND_Base_MS\", \"Checked\": true, \"RowOrder\": 6, \"ShortName\": \"RS\"}, {\"Name\": \"DEMAND_Base_MS_E\", \"Checked\": true, \"RowOrder\": 7, \"ShortName\": \"RS\"}, {\"Name\": \"DEMAND_High_BAU\", \"Checked\": true, \"RowOrder\": 8, \"ShortName\": \"RS\"}, {\"Name\": \"DEMAND_High_MS\", \"Checked\": true, \"RowOrder\": 9, \"ShortName\": \"RS\"}, {\"Name\": \"DEMAND_High_MS_E\", \"Checked\": true, \"RowOrder\": 10, \"ShortName\": \"RS\"}, {\"Name\": \"Emission_AP_TRA_GJ_v2\", \"Checked\": true, \"RowOrder\": 11, \"ShortName\": \"RS\"}, {\"Name\": \"Emission_CO2\", \"Checked\": true, \"RowOrder\": 12, \"ShortName\": \"RS\"}, {\"Name\": \"Price_ELC_V2\", \"Checked\": true, \"RowOrder\": 13, \"ShortName\": \"RS\"}, {\"Name\": \"Price_Import_v5_BioHigh\", \"Checked\": true, \"RowOrder\": 14, \"ShortName\": \"RS\"}, {\"Name\": \"Price_Import_v5_BioMedium\", \"Checked\": true, \"RowOrder\": 15, \"ShortName\": \"RS\"}, {\"Name\": \"T_CO2_Bana_Kommun\", \"Checked\": true, \"RowOrder\": 16, \"ShortName\": \"RS\"}, {\"Name\": \"T_CO2_Bana_Region\", \"Checked\": true, \"RowOrder\": 17, \"ShortName\": \"RS\"}, {\"Name\": \"T_CO2_Budget_Kommun\", \"Checked\": true, \"RowOrder\": 18, \"ShortName\": \"RS\"}, {\"Name\": \"T_CO2_Budget_Region\", \"Checked\": true, \"RowOrder\": 19, \"ShortName\": \"RS\"}, {\"Name\": \"T_DeliveryCosts\", \"Checked\": false, \"RowOrder\": 20, \"ShortName\": \"RS\"}, {\"Name\": \"Taxes_Bio_2025\", \"Checked\": true, \"RowOrder\": 21, \"ShortName\": \"RS\"}, {\"Name\": \"Taxes_CO2_TRA\", \"Checked\": true, \"RowOrder\": 22, \"ShortName\": \"RS\"}, {\"Name\": \"Taxes_Energy\", \"Checked\": true, \"RowOrder\": 23, \"ShortName\": \"RS\"}, {\"Name\": \"X_AAA\", \"Checked\": true, \"RowOrder\": 24, \"ShortName\": \"RS\"}, {\"Name\": \"X_BEV_PHEV_Low\", \"Checked\": true, \"RowOrder\": 25, \"ShortName\": \"RS\"}, {\"Name\": \"X_Car_Bonus\", \"Checked\": true, \"RowOrder\": 26, \"ShortName\": \"RS\"}, {\"Name\": \"X_Infrastructure\", \"Checked\": true, \"RowOrder\": 27, \"ShortName\": \"RS\"}, {\"Name\": \"X_PriceGasHigh\", \"Checked\": true, \"RowOrder\": 28, \"ShortName\": \"RS\"}, {\"Name\": \"X_Red_Blending\", \"Checked\": true, \"RowOrder\": 29, \"ShortName\": \"RS\"}, {\"Name\": \"X_Red_Blending_2045\", \"Checked\": true, \"RowOrder\": 30, \"ShortName\": \"RS\"}, {\"Name\": \"X_Reduktionsplikt\", \"Checked\": true, \"RowOrder\": 31, \"ShortName\": \"RS\"}, {\"Name\": \"X_Reduktionsplikt_2045\", \"Checked\": true, \"RowOrder\": 32, \"ShortName\": \"RS\"}]","CreatedOn":"2022-11-17 12:58","DisplayCreatedOn":"2022-11-17 12:58","UserName":"jonfor"},{"SavedGroupId":30,"GroupName":"TEST_2_STHLM","GroupType":"Scenario","Settings":"[{\"Name\": \"BASE\", \"Checked\": true, \"RowOrder\": 0, \"ShortName\": \"B\"}, {\"Name\": \"B-NewTechs_SUP\", \"Checked\": false, \"RowOrder\": 1, \"ShortName\": \"SR\"}, {\"Name\": \"B-NewTechs_TRA\", \"Checked\": true, \"RowOrder\": 2, \"ShortName\": \"SR\"}, {\"Name\": \"SysSettings\", \"Checked\": true, \"RowOrder\": 3, \"ShortName\": \"SS\"}, {\"Name\": \"DEMAND_Base_BAU\", \"Checked\": true, \"RowOrder\": 4, \"ShortName\": \"RS\"}, {\"Name\": \"xxx-TEST\", \"Checked\": false, \"RowOrder\": 5, \"ShortName\": \"RS\"}]","CreatedOn":"2022-11-21 20:49","DisplayCreatedOn":"2022-11-21 20:49","UserName":"jonfor"}]